Metadata-Version: 2.1
Name: postgrey
Version: 0.0.1
Summary: 🐘 Simple, Fast, Async & ORM PostgreSQL database client based on Asyncpg for Python.
Home-page: https://github.com/5elenay/postgrey/
Author: 5elenay
Author-email: 
License: MIT
Project-URL: Bug Tracker, https://github.com/5elenay/postgrey/issues
Keywords: postgres,postgresql,orm,database,client,fast,asyncio
Platform: UNKNOWN
Classifier: Development Status :: 4 - Beta
Classifier: Intended Audience :: Developers
Classifier: Operating System :: OS Independent
Classifier: License :: OSI Approved :: MIT License
Classifier: Programming Language :: Python :: 3
Requires-Python: >=3.6.0
